[
  {
    "_id": "62487b94f568628e653dc7e6",
    "product_index": 0,
    "discription": "irure labore magna esse enim eu duis esse ipsum pariatur pariatur mollit nostrud elit sit ipsum mollit veniam aliquip ut",
    "price": "$44.00",
    "shipping": "$9.03",
    "ratting": 5,
    "img": "https://apollotran.b-cdn.net/prestashop/leo_tracy/39-home_default/printed-summer-dress.jpghttps://apollotran.b-cdn.net/prestashop/leo_tracy/39-home_default/printed-summer-dress.jpg",
    "quantity": 1,
    "color_family": "red",
    "name": "Red dress"
  },
  {
    "_id": "62487b947f9180646f4765d5",
    "product_index": 1,
    "discription": "incididunt do cupidatat ad aliqua id sit irure commodo mollit nulla nulla elit occaecat tempor incididunt proident quis irure velit",
    "price": "$49.82",
    "shipping": "$6.23",
    "ratting": 3,
    "img": "https://apollotran.b-cdn.net/prestashop/leo_tracy/31-home_default/blouse.jpg",
    "quantity": 1,
    "color_family": "black",
    "name": "Black Jacket"
  },
  {
    "_id": "62487b94ca3212be2a23fbe5",
    "product_index": 2,
    "discription": "et labore amet aute sint labore Lorem anim esse non voluptate qui dolor elit voluptate consectetur irure et anim laboris",
    "price": "$38.47",
    "shipping": "$6.93",
    "ratting": 4,
    "img": "https://apollotran.b-cdn.net/prestashop/leo_tracy/37-home_default/printed-summer-dress.jpg",
    "quantity": 1,
    "color_family": "red",
    "name": "Printed summer dress"
  },
  {
    "_id": "62487b944ff27183063bddc9",
    "product_index": 3,
    "discription": "irure amet occaecat amet ullamco adipisicing aliqua qui sint amet aliqua sit enim eiusmod adipisicing sunt nulla ex minim incididunt",
    "price": "$48.15",
    "shipping": "$10.99",
    "ratting": 5,
    "img": "https://apollotran.b-cdn.net/prestashop/leo_tracy/themes/leo_tracy/assets/img/modules/appagebuilder/images/banner3.jpg",
    "quantity": 1,
    "color_family": "brown",
    "name": "Brown top"
  },
  {
    "_id": "62487b941b9dfb1de6ac9b93",
    "product_index": 4,
    "discription": "in quis eiusmod adipisicing nulla commodo est dolor quis incididunt reprehenderit cillum eu sit dolor fugiat elit nostrud laborum quis",
    "price": "$82.54",
    "shipping": "$13.99",
    "ratting": 5,
    "img": "https://apollotran.b-cdn.net/prestashop/leo_tracy/40-home_default/printed-chiffon-dress.jpg",
    "quantity": 1,
    "color_family": "yellow",
    "name": "Printed chiffon dress"
  },
  {
    "_id": "62487b94bc7845eea16ee50e",
    "product_index": 5,
    "discription": "nulla irure veniam cillum officia ad culpa veniam qui quis minim ad tempor labore ea deserunt consectetur cupidatat ad labore",
    "price": "$97.08",
    "shipping": "$5.94",
    "ratting": 3,
    "img": "https://apollotran.b-cdn.net/prestashop/leo_tracy/32-home_default/printed-dress.jpg",
    "quantity": 1,
    "color_family": "darkblue",
    "name": "Printed full shirt"
  },
  {
    "_id": "62487b94a7023216d2b42d2f",
    "product_index": 6,
    "discription": "dolor in qui velit dolore aliquip id irure nostrud labore aliqua tempor Lorem laboris enim ullamco quis commodo exercitation quis",
    "price": "$56.25",
    "shipping": "$6.89",
    "ratting": 4,
    "img": "https://apollotran.b-cdn.net/prestashop/leo_tracy/44-home_default/printed-summer-dress.jpg",
    "quantity": 1,
    "color_family": "mix",
    "name": "Printed summer dress"
  },
  {
    "_id": "62487b94e1a670860a76a2c1",
    "product_index": 7,
    "discription": "ea sunt quis in nostrud consequat excepteur eiusmod aliquip veniam in commodo reprehenderit adipisicing occaecat dolor cupidatat laboris excepteur proident",
    "price": "$50.79",
    "shipping": "$32.19",
    "ratting": 3,
    "img": "https://apollotran.b-cdn.net/prestashop/leo_tracy/33-home_default/printed-dress.jpg",
    "quantity": 1,
    "color_family": "black",
    "name": "Printed darkblue shirt"
  }
]